mirrorctl/__init__.py
mirrorctl/cli.py
mirrorctl-0.1.0.dist-info/METADATA
mirrorctl-0.1.0.dist-info/WHEEL
mirrorctl-0.1.0.dist-info/entry_points.txt
mirrorctl-0.1.0.dist-info/top_level.txt
mirrorctl-0.1.0.dist-info/RECORD
