Metadata-Version: 2.4
Name: mirrorctl
Version: 0.1.0
Summary: Manage mirror sources for common development tools
Requires-Python: >=3.9
